README.txt
setup.py
docs/HISTORY.txt
docs/INSTALL.txt
docs/LICENSE.GPL
docs/LICENSE.txt
src/collective/__init__.py
src/collective.steps.egg-info/PKG-INFO
src/collective.steps.egg-info/SOURCES.txt
src/collective.steps.egg-info/dependency_links.txt
src/collective.steps.egg-info/entry_points.txt
src/collective.steps.egg-info/namespace_packages.txt
src/collective.steps.egg-info/not-zip-safe
src/collective.steps.egg-info/requires.txt
src/collective.steps.egg-info/top_level.txt
src/collective/steps/__init__.py
src/collective/steps/common.py
src/collective/steps/config.py
src/collective/steps/members.py
src/collective/steps/profile.py
src/collective/steps/tests.py