Metadata-Version: 1.0
Name: collective.steps
Version: 0.3
Summary: Steps to manage a plone site with Stepper by Makina Corpus
Home-page: http://svn.plone.org/svn/collective/collective.steps
Author: Jean-Michel FRANCOIS aka toutpt
Author-email: jeanmichel.francois@makina-corpus.com
License: GPL
Platform: UNKNOWN
Classifier: Framework :: Plone
Classifier: Programming Language :: Python
Classifier: Topic :: Software Development :: Libraries :: Python Modules
